privkit/__init__.py
privkit/attacks/__init__.py
privkit/attacks/attack.py
privkit/attacks/hw.py
privkit/attacks/map_matching.py
privkit/attacks/peba.py
privkit/attacks/topN.py
privkit/data/__init__.py
privkit/data/data_type.py
privkit/data/facial_data.py
privkit/data/location_data.py
privkit/data/tabular_data.py
privkit/datasets/NCSRD_DS_5GDDoS_dataset.py
privkit/datasets/__init__.py
privkit/datasets/cabspotting_dataset.py
privkit/datasets/dataset.py
privkit/datasets/geolife_dataset.py
privkit/datasets/sketchfab_dataset.py
privkit/metrics/__init__.py
privkit/metrics/adv_error.py
privkit/metrics/cmc.py
privkit/metrics/f1_score.py
privkit/metrics/face_detection_accuracy.py
privkit/metrics/fi_distance.py
privkit/metrics/metric.py
privkit/metrics/quality_loss.py
privkit/metrics/roc.py
privkit/metrics/ss_index.py
privkit/ppms/__init__.py
privkit/ppms/adaptive_geo_ind.py
privkit/ppms/centroid_voxel.py
privkit/ppms/clustering_geo_ind.py
privkit/ppms/hash.py
privkit/ppms/laplace.py
privkit/ppms/merge_two_faces.py
privkit/ppms/planar_laplace.py
privkit/ppms/point_mesh_point.py
privkit/ppms/ppm.py
privkit/ppms/privacy_aware_remapping.py
privkit/ppms/smooth_knn.py
privkit/ppms/tapering.py
privkit/ppms/uniform_noise.py
privkit/ppms/uniform_remapping.py
privkit/ppms/va_gi.py
privkit/utils/__init__.py
privkit/utils/constants.py
privkit/utils/dev_utils.py
privkit/utils/discrete_utils.py
privkit/utils/face_utils.py
privkit/utils/geo_utils.py
privkit/utils/io_utils.py
privkit/utils/plot_utils.py
privkit/utils/training_utils.py
privkit-0.5.0.dist-info/METADATA
privkit-0.5.0.dist-info/WHEEL
privkit-0.5.0.dist-info/licenses/LICENSE
privkit-0.5.0.dist-info/RECORD
