Metadata-Version: 2.4
Name: privkit
Version: 0.5.0
Summary: Privkit is a privacy toolkit that provides methods for privacy analysis. It implements different data types, privacy-preserving mechanisms, attacks, and privacy/utility metrics.
Project-URL: Homepage, https://privkit.fc.up.pt
Project-URL: Source, https://github.com/privkit/privkit
Project-URL: Issues, https://github.com/privkit/privkit/issues
Project-URL: Documentation, https://privkit.fc.up.pt
License-File: LICENSE
Classifier: License :: OSI Approved :: BSD License
Classifier: Operating System :: OS Independent
Classifier: Programming Language :: Python
Classifier: Topic :: Scientific/Engineering
Requires-Python: >=3
Requires-Dist: deepface>=0.0.93
Requires-Dist: matplotlib>=3.9.2
Requires-Dist: networkx>=3.4.2
Requires-Dist: numpy==1.26.4
Requires-Dist: open3d>=0.18.0
Requires-Dist: osmnx>=2.0.0
Requires-Dist: pandas>=2.2.3
Requires-Dist: pyproj>=3.7.0
Requires-Dist: scikit-image>=0.24.0
Requires-Dist: scikit-learn>=1.5.2
Requires-Dist: tf-keras>=2.18.0
Requires-Dist: torch>=2.5.1
